{"Status":{"Module":27,"FriendlyName":["Sonoff"],"Topic":"Lampe1","ButtonTopic":"0","Power":0,"PowerOnState":3,"LedState":1,"SaveData":0,"SaveState":1,"ButtonRetain":0,"PowerRetain":0},"StatusPRM":{"Baudrate":115200,"GroupTopic":"sonoffs","OtaUrl":"http://sonoff.maddox.co.uk/tasmota/sonoff.bin","RestartReason":"Software/System restart","Uptime":"0T00:00:20","StartupUTC":"2018-09-04T16:31:18","Sleep":1,"BootCount":141,"SaveCount":4432,"SaveAddress":"FB000"},"StatusFWR":{"Version":"6.2.0","BuildDateTime":"2018.09.02 07:59:37","Boot":31,"Core":"2_3_0","SDK":"1.5.3(aec24ac9)"},"StatusLOG":{"SerialLog":0,"WebLog":2,"SysLog":0,"LogHost":"","LogPort":514,"SSId":["arminseins",""],"TelePeriod":300,"SetOption":["04008009","55818000","00000001"]},"StatusMEM":{"ProgramSize":456,"Free":544,"Heap":19,"ProgramFlashSize":1024,"FlashSize":1024,"FlashMode":3,"Features":["00000407","0F50A794","24000000","020B979E","00000000"]},"StatusNET":{"Hostname":"Lampe1-1681","IPAddress":"192.168.1.11","Gateway":"192.168.1.1","Subnetmask":"255.255.255.0","DNSServer":"192.168.1.1","Mac":"68:C6:3A:BD:A6:91","Webserver":2,"WifiConfig":5},"StatusMQT":{"MqttHost":"192.168.178.2","MqttPort":1883,"MqttClientMask":"DVES_%06X","MqttClient":"DVES_BDA691","MqttUser":"DVES_USER","MqttType":1,"MAX_PACKET_SIZE":1000,"KEEPALIVE":15},"StatusTIM":{"UTC":"Tue Sep 04 16:31:38 2018","Local":"Tue Sep 04 18:31:38 2018","StartDST":"Sun Mar 25 02:00:00 2018","EndDST":"Sun Oct 28 03:00:00 2018","Timezone":2,"Sunrise":"07:11","Sunset":"20:27"},"StatusSNS":{"Time":"2018-09-04T18:31:38","Switch2":"OFF"},"StatusSTS":{"Time":"2018-09-04T18:31:38","Uptime":"0T00:00:20","Vcc":3.167,"POWER1":"OFF","Dimmer":90,"Color":"00E51F00","HSBColor":"128,100,90","Channel":[0,90,12,0],"Scheme":3,"Fade":"OFF","Speed":1,"LedTable":"OFF","Wifi":{"AP":1,"SSId":"arminseins","RSSI":58,"APMac":"28:C6:8E:B3:C8:9C"}}}